realty/__init__.py
realty/version.py
realty/landwatch/__init__.py
realty/landwatch/defaults.py
realty/landwatch/query.py
realty/landwatch/details/__init__.py
realty/landwatch/details/details.py
realty/realtor/__init__.py
realty/realtor/defaults.py
realty/realtor/query.py
realty/realtor/details/__init__.py
realty/realtor/details/sale.py
realty/zillow/__init__.py
realty/zillow/defaults.py
realty/zillow/query.py
realty/zillow/details/__init__.py
realty/zillow/details/details_page.py
realty/zillow/details/rental_apartment.py
realty/zillow/details/rental_home.py
realty/zillow/details/sale.py
realty/zillow/details/scrape.py
py_realty-0.1.1.dist-info/LICENSE
py_realty-0.1.1.dist-info/METADATA
py_realty-0.1.1.dist-info/WHEEL
py_realty-0.1.1.dist-info/top_level.txt
py_realty-0.1.1.dist-info/RECORD
