Metadata-Version: 2.1
Name: py-realty
Version: 0.1.1
Summary: Python real estate scraping library
Home-page: https://github.com/JakubPolanowski/PY-Realty
Author: Jakub Polanowski
License: GNU AFFERO GENERAL PUBLIC LICENSE
Project-URL: Source, https://github.com/JakubPolanowski/PY-Realty
Classifier: Development Status :: 2 - Pre-Alpha
Classifier: Environment :: Web Environment
Classifier: Intended Audience :: Developers
Classifier: License :: OSI Approved :: GNU Affero General Public License v3 or later (AGPLv3+)
Classifier: Natural Language :: English
Classifier: Operating System :: OS Independent
Classifier: Programming Language :: Python
Classifier: Programming Language :: Python :: 3
Classifier: Programming Language :: Python :: 3.10
Classifier: Programming Language :: Python :: 3.11
Classifier: Programming Language :: Python :: 3 :: Only
Classifier: Programming Language :: Python :: Implementation :: CPython
Classifier: Programming Language :: Python :: Implementation :: PyPy
Classifier: Topic :: Internet :: WWW/HTTP
Classifier: Topic :: Software Development :: Libraries
Requires-Python: >=3.10, <4
License-File: LICENSE
Requires-Dist: beautifulsoup4 (>=4.11.1)
Requires-Dist: numpy (>=1.24.0)
Requires-Dist: requests (>=2.28.1)
